[
    {
      "inputs": [],
      "stateMutability": "nonpayable",
      "type": "constructor"
    },
    {
      "anonymous": false,
      "inputs": [
        {
          "indexed": false,
          "internalType": "address",
          "name": "_addr",
          "type": "address"
        },
        {
          "indexed": false,
          "internalType": "uint256",
          "name": "_amount",
          "type": "uint256"
        }
      ],
      "name": "SnatchPool",
      "type": "event"
    },
    {
      "anonymous": false,
      "inputs": [
        {
          "indexed": false,
          "internalType": "address",
          "name": "_owner",
          "type": "address"
        },
        {
          "indexed": false,
          "internalType": "address",
          "name": "_addr",
          "type": "address"
        },
        {
          "indexed": false,
          "internalType": "uint256",
          "name": "_amount",
          "type": "uint256"
        }
      ],
      "name": "WithdrawPool",
      "type": "event"
    },
    {
      "inputs": [],
      "name": "durationEndTime",
      "outputs": [
        {
          "internalType": "uint256",
          "name": "",
          "type": "uint256"
        }
      ],
      "stateMutability": "view",
      "type": "function"
    },
    {
      "inputs": [],
      "name": "durationTime",
      "outputs": [
        {
          "internalType": "uint256",
          "name": "",
          "type": "uint256"
        }
      ],
      "stateMutability": "view",
      "type": "function"
    },
    {
      "inputs": [],
      "name": "increaseRange",
      "outputs": [
        {
          "internalType": "uint256",
          "name": "",
          "type": "uint256"
        }
      ],
      "stateMutability": "view",
      "type": "function"
    },
    {
      "inputs": [],
      "name": "platformAddress",
      "outputs": [
        {
          "internalType": "address",
          "name": "",
          "type": "address"
        }
      ],
      "stateMutability": "view",
      "type": "function"
    },
    {
      "inputs": [],
      "name": "snatchCount",
      "outputs": [
        {
          "internalType": "uint256",
          "name": "",
          "type": "uint256"
        }
      ],
      "stateMutability": "view",
      "type": "function"
    },
    {
      "inputs": [],
      "name": "totalAmount",
      "outputs": [
        {
          "internalType": "uint256",
          "name": "",
          "type": "uint256"
        }
      ],
      "stateMutability": "view",
      "type": "function"
    },
    {
      "inputs": [],
      "name": "totalSnatchCount",
      "outputs": [
        {
          "internalType": "uint256",
          "name": "",
          "type": "uint256"
        }
      ],
      "stateMutability": "view",
      "type": "function"
    },
    {
      "inputs": [
        {
          "internalType": "uint256",
          "name": "",
          "type": "uint256"
        }
      ],
      "name": "winnerAddresses",
      "outputs": [
        {
          "internalType": "address",
          "name": "",
          "type": "address"
        }
      ],
      "stateMutability": "view",
      "type": "function"
    },
    {
      "inputs": [
        {
          "internalType": "address",
          "name": "",
          "type": "address"
        },
        {
          "internalType": "uint256",
          "name": "",
          "type": "uint256"
        }
      ],
      "name": "winnerMap",
      "outputs": [
        {
          "internalType": "address",
          "name": "winner",
          "type": "address"
        },
        {
          "internalType": "uint256",
          "name": "count",
          "type": "uint256"
        },
        {
          "internalType": "uint256",
          "name": "scount",
          "type": "uint256"
        },
        {
          "internalType": "uint256",
          "name": "amount",
          "type": "uint256"
        },
        {
          "internalType": "uint256",
          "name": "winTime",
          "type": "uint256"
        }
      ],
      "stateMutability": "view",
      "type": "function"
    },
    {
      "inputs": [
        {
          "internalType": "uint256",
          "name": "",
          "type": "uint256"
        }
      ],
      "name": "winners",
      "outputs": [
        {
          "internalType": "address",
          "name": "winner",
          "type": "address"
        },
        {
          "internalType": "uint256",
          "name": "count",
          "type": "uint256"
        },
        {
          "internalType": "uint256",
          "name": "scount",
          "type": "uint256"
        },
        {
          "internalType": "uint256",
          "name": "amount",
          "type": "uint256"
        },
        {
          "internalType": "uint256",
          "name": "winTime",
          "type": "uint256"
        }
      ],
      "stateMutability": "view",
      "type": "function"
    },
    {
      "inputs": [],
      "name": "getCurrentSnatchInfo",
      "outputs": [
        {
          "internalType": "address",
          "name": "lastOwner",
          "type": "address"
        },
        {
          "internalType": "address",
          "name": "tempOwner",
          "type": "address"
        },
        {
          "internalType": "uint256",
          "name": "amount",
          "type": "uint256"
        },
        {
          "internalType": "uint256",
          "name": "submitAmount",
          "type": "uint256"
        },
        {
          "internalType": "uint256",
          "name": "lastAmount",
          "type": "uint256"
        },
        {
          "internalType": "uint256",
          "name": "lastTime",
          "type": "uint256"
        },
        {
          "internalType": "uint256",
          "name": "startTime",
          "type": "uint256"
        },
        {
          "internalType": "uint256",
          "name": "durationEndTime",
          "type": "uint256"
        },
        {
          "internalType": "uint256",
          "name": "durationTime",
          "type": "uint256"
        },
        {
          "internalType": "uint256",
          "name": "increaseRange",
          "type": "uint256"
        },
        {
          "internalType": "uint256",
          "name": "totalAmount",
          "type": "uint256"
        },
        {
          "internalType": "uint256",
          "name": "snatchCount",
          "type": "uint256"
        },
        {
          "internalType": "uint256",
          "name": "totalSnatchCount",
          "type": "uint256"
        }
      ],
      "stateMutability": "view",
      "type": "function"
    },
    {
      "inputs": [],
      "name": "getWinnerAddresses",
      "outputs": [
        {
          "internalType": "address[]",
          "name": "_winners",
          "type": "address[]"
        }
      ],
      "stateMutability": "view",
      "type": "function"
    },
    {
      "inputs": [
        {
          "internalType": "address",
          "name": "_platform",
          "type": "address"
        }
      ],
      "name": "setPlatform",
      "outputs": [],
      "stateMutability": "nonpayable",
      "type": "function"
    },
    {
      "inputs": [
        {
          "internalType": "uint256",
          "name": "_durationTime",
          "type": "uint256"
        },
        {
          "internalType": "uint256",
          "name": "_durationEndTime",
          "type": "uint256"
        }
      ],
      "name": "setDuration",
      "outputs": [],
      "stateMutability": "nonpayable",
      "type": "function"
    },
    {
      "inputs": [
        {
          "internalType": "uint256",
          "name": "_rate",
          "type": "uint256"
        },
        {
          "internalType": "uint256",
          "name": "_increaseRange",
          "type": "uint256"
        }
      ],
      "name": "setPlatformRate",
      "outputs": [],
      "stateMutability": "nonpayable",
      "type": "function"
    },
    {
      "inputs": [],
      "name": "getNow",
      "outputs": [
        {
          "internalType": "uint256",
          "name": "",
          "type": "uint256"
        }
      ],
      "stateMutability": "view",
      "type": "function"
    },
    {
      "inputs": [],
      "name": "snatchPool",
      "outputs": [],
      "stateMutability": "payable",
      "type": "function"
    },
    {
      "inputs": [],
      "name": "withdrawPool",
      "outputs": [],
      "stateMutability": "nonpayable",
      "type": "function"
    },
    {
      "inputs": [],
      "name": "otherWithdraw",
      "outputs": [],
      "stateMutability": "nonpayable",
      "type": "function"
    }
]